ffx/__init__.py
ffx/encrypter.py
ffx/exceptions.py
ffx/integer.py
ffx/utils.py
libffx-1.0.2.dist-info/licenses/LICENSE
libffx-1.0.2.dist-info/METADATA
libffx-1.0.2.dist-info/WHEEL
libffx-1.0.2.dist-info/top_level.txt
libffx-1.0.2.dist-info/RECORD
