Metadata-Version: 2.4
Name: libffx
Version: 1.0.2
Summary: FFX - Format Preserving Encryption (NIST FFX-A2 mode of operation)
Author-email: "Kevin P. Dyer" <kpdyer@gmail.com>
Maintainer-email: "Kevin P. Dyer" <kpdyer@gmail.com>
License: MIT
Project-URL: Homepage, https://github.com/kpdyer/libffx
Project-URL: Repository, https://github.com/kpdyer/libffx
Project-URL: Issues, https://github.com/kpdyer/libffx/issues
Keywords: cryptography,encryption,format-preserving,ffx,fpe,aes
Classifier: Development Status :: 4 - Beta
Classifier: Intended Audience :: Developers
Classifier: License :: OSI Approved :: MIT License
Classifier: Operating System :: OS Independent
Classifier: Programming Language :: Python :: 3
Classifier: Programming Language :: Python :: 3.9
Classifier: Programming Language :: Python :: 3.10
Classifier: Programming Language :: Python :: 3.11
Classifier: Programming Language :: Python :: 3.12
Classifier: Programming Language :: Python :: 3.13
Classifier: Topic :: Security :: Cryptography
Requires-Python: >=3.9
License-File: LICENSE
Requires-Dist: gmpy2>=2.1.0
Requires-Dist: pycryptodome>=3.15.0
Provides-Extra: dev
Requires-Dist: pytest>=7.0; extra == "dev"
Requires-Dist: pytest-cov>=4.0; extra == "dev"
Requires-Dist: mypy>=1.0; extra == "dev"
Dynamic: license-file
